README.md
setup.py
descformats/__init__.py
descformats/base.py
descformats.egg-info/PKG-INFO
descformats.egg-info/SOURCES.txt
descformats.egg-info/dependency_links.txt
descformats.egg-info/top_level.txt
descformats/pz/__init__.py
descformats/pz/pz.py
descformats/tx/__init__.py
descformats/tx/tx.py