Metadata-Version: 1.2
Name: descformats
Version: 0.0.5
Summary: Interface wrappers to file types in DESC pipelines
Home-page: https://github.com/LSSTDESC/DESCFormats
Maintainer: Joe Zuntz
License: MIT
Platform: UNKNOWN
Classifier: Intended Audience :: Developers
Classifier: Intended Audience :: Science/Research
Classifier: License :: OSI Approved :: MIT License
Classifier: Programming Language :: Python :: 3.6
Requires-Python: >=3
